<?xml version="1.0" encoding="utf-8" ?><dwsync><file name="glyphicons-halflings-regular.eot" server="evolucionestrategica.com.mx//public_html/wp-content/themes/" local="3486644051" remote="318763443883034232" Dst="-1" /><file name="glyphicons-halflings-regular.svg" server="evolucionestrategica.com.mx//public_html/wp-content/themes/" local="3486644051" remote="318763443883034232" Dst="-1" /><file name="glyphicons-halflings-regular.woff" server="evolucionestrategica.com.mx//public_html/wp-content/themes/" local="3486644051" remote="318763443883034232" Dst="-1" /><file name="glyphicons-halflings-regular.ttf" server="evolucionestrategica.com.mx//public_html/wp-content/themes/" local="3486644051" remote="318763443883034292" Dst="-1" /><file name="glyphicons-halflings-regular.eot" server="abarroteraperma.com/wp-content/themes/" local="3486644051" remote="318763443908481972" Dst="-1" /><file name="glyphicons-halflings-regular.svg" server="abarroteraperma.com/wp-content/themes/" local="3486644051" remote="318763443908481972" Dst="-1" /><file name="glyphicons-halflings-regular.woff" server="abarroteraperma.com/wp-content/themes/" local="3486644051" remote="318763443908481972" Dst="-1" /><file name="ubuntu-b.eot" server="abarroteraperma.com/wp-content/themes/" local="3515522190" remote="318763443908481972" Dst="-1" /><file name="glyphicons-halflings-regular.ttf" server="abarroteraperma.com/wp-content/themes/" local="3486644051" remote="318763443908481972" Dst="-1" /><file name="ubuntu-b.ttf" server="abarroteraperma.com/wp-content/themes/" local="3515522190" remote="318763443908481972" Dst="-1" /><file name="ubuntu-b.svg" server="abarroteraperma.com/wp-content/themes/" local="3515522190" remote="318763443908481972" Dst="-1" /><file name="ubuntu-b.woff" server="abarroteraperma.com/wp-content/themes/" local="3515522190" remote="318763443908481972" Dst="-1" /><file name="ubuntu-b.woff2" server="abarroteraperma.com/wp-content/themes/" local="3515522190" remote="318763443908481972" Dst="-1" /><file name="ubuntu-l.eot" server="abarroteraperma.com/wp-content/themes/" local="3515522190" remote="318763443908481972" Dst="-1" /><file name="ubuntu-l.svg" server="abarroteraperma.com/wp-content/themes/" local="3515522190" remote="318763443908481972" Dst="-1" /><file name="ubuntu-l.woff" server="abarroteraperma.com/wp-content/themes/" local="3515522190" remote="318763443908481972" Dst="-1" /><file name="ubuntu-l.woff2" server="abarroteraperma.com/wp-content/themes/" local="3515522190" remote="318763443908481972" Dst="-1" /><file name="ubuntu-l.ttf" server="abarroteraperma.com/wp-content/themes/" local="3515522190" remote="318763443908481972" Dst="-1" /><file name="ubuntu-m.eot" server="abarroteraperma.com/wp-content/themes/" local="3515522190" remote="318763443908481972" Dst="-1" /><file name="ubuntu-m.woff" server="abarroteraperma.com/wp-content/themes/" local="3515522190" remote="318763443908481972" Dst="-1" /><file name="ubuntu-m.svg" server="abarroteraperma.com/wp-content/themes/" local="3515522190" remote="318763443908481972" Dst="-1" /><file name="ubuntu-m.ttf" server="abarroteraperma.com/wp-content/themes/" local="3515522190" remote="318763443908481972" Dst="-1" /><file name="ubuntu-m.woff2" server="abarroteraperma.com/wp-content/themes/" local="3515522190" remote="318763443908481972" Dst="-1" /><file name="ubuntu-r.eot" server="abarroteraperma.com/wp-content/themes/" local="3515522190" remote="318763443908481972" Dst="-1" /><file name="ubuntu-r.svg" server="abarroteraperma.com/wp-content/themes/" local="3515522190" remote="318763443908481972" Dst="-1" /><file name="ubuntu-r.ttf" server="abarroteraperma.com/wp-content/themes/" local="3515522190" remote="318763443908481972" Dst="-1" /><file name="ubuntu-r.woff" server="abarroteraperma.com/wp-content/themes/" local="3515522190" remote="318763443908481972" Dst="-1" /><file name="ubuntu-r.woff2" server="abarroteraperma.com/wp-content/themes/" local="3515522190" remote="318763443908481972" Dst="-1" /></dwsync>